refuel/__init__.py
refuel/client.py
refuel/constants.py
refuel/types.py
refuel/utils.py
refuel/tests/__init__.py
refuel/tests/conftest.py
refuel/tests/test_client.py
refuel-0.15.15.dist-info/LICENSE
refuel-0.15.15.dist-info/METADATA
refuel-0.15.15.dist-info/WHEEL
refuel-0.15.15.dist-info/top_level.txt
refuel-0.15.15.dist-info/RECORD
