Metadata-Version: 2.2
Name: refuel
Version: 0.15.15
Summary: Refuel platform SDK
Author-email: "Refuel.ai" <support@refuel.ai>
License: Copyright (c) 2023, Refuel AI, Inc.
Project-URL: Homepage, https://refuel.ai
Classifier: Development Status :: 5 - Production/Stable
Classifier: Programming Language :: Python
Classifier: Programming Language :: Python :: 3
Classifier: Topic :: Software Development :: Libraries :: Python Modules
Classifier: Topic :: Scientific/Engineering :: Artificial Intelligence
Requires-Python: >=3.6
License-File: LICENSE
Requires-Dist: numpy==1.26.4
Requires-Dist: pandas>=1.3.0
Requires-Dist: pydantic>=1.10.9
Requires-Dist: requests_futures>=1.0.0
Requires-Dist: loguru>=0.5.0
Requires-Dist: jsonschema>=4.19.0
Requires-Dist: tenacity==8.2.3
Provides-Extra: dev
Requires-Dist: black; extra == "dev"
Requires-Dist: pip-tools; extra == "dev"
Requires-Dist: pytest; extra == "dev"
Requires-Dist: pytest-asyncio; extra == "dev"
Requires-Dist: pytest-mock; extra == "dev"
Requires-Dist: pre-commit; extra == "dev"
